redcaptcha_challenger/__init__.py
redcaptcha_challenger/py.typed
redcaptcha_challenger-0.0.1.dist-info/METADATA
redcaptcha_challenger-0.0.1.dist-info/WHEEL
redcaptcha_challenger-0.0.1.dist-info/licenses/LICENSE
redcaptcha_challenger-0.0.1.dist-info/RECORD
