Metadata-Version: 2.4
Name: redcaptcha-challenger
Version: 0.0.1
Summary: 👾 Gracefully face the Xiaohongshu RedCaptcha
Project-URL: Homepage, https://github.com/QIN2DIM/redcaptcha-challenger
Project-URL: Documentation, https://github.com/QIN2DIM/redcaptcha-challenger
Project-URL: Repository, https://github.com/QIN2DIM/redcaptcha-challenger.git
Project-URL: Issues, https://github.com/QIN2DIM/redcaptcha-challenger/issues
Project-URL: Changelog, https://github.com/QIN2DIM/redcaptcha-challenger/blob/master/CHANGELOG.md
Author-email: QIN2DIM <yaoqinse@gmail.com>, Bingjie Yan <bj.yan.pa@qq.com>
License-Expression: GPL-3.0-or-later
License-File: LICENSE
Keywords: agent,large language model,redcaptcha,redcaptcha-challenger,redcaptcha-solver
Classifier: Development Status :: 3 - Alpha
Classifier: Intended Audience :: Developers
Classifier: Programming Language :: Python :: 3
Classifier: Programming Language :: Python :: 3 :: Only
Classifier: Programming Language :: Python :: 3.10
Classifier: Programming Language :: Python :: 3.11
Classifier: Programming Language :: Python :: 3.12
Classifier: Programming Language :: Python :: 3.13
Classifier: Topic :: Scientific/Engineering :: Artificial Intelligence
Classifier: Topic :: Scientific/Engineering :: Image Processing
Classifier: Topic :: Scientific/Engineering :: Image Recognition
Classifier: Topic :: Software Development
Requires-Python: >=3.12
Requires-Dist: camoufox[geoip]>=0.4.11
Requires-Dist: httpx[http2]>=0.28.1
Requires-Dist: loguru>=0.7.3
Requires-Dist: numpy>=2.3.1
Requires-Dist: pillow>=11.3.0
Requires-Dist: playwright>=1.53.0
Requires-Dist: pydantic-settings>=2.10.1
Requires-Dist: tenacity>=9.1.2
Requires-Dist: typer>=0.16.0
Provides-Extra: dataset
Requires-Dist: typer; extra == 'dataset'
Provides-Extra: server
Requires-Dist: fastapi[all]>=0.115.12; extra == 'server'
